md2gemini/__init__.py
md2gemini/__main__.py
md2gemini/renderers.py
md2gemini/unitable.py
md2gemini-1.9.1.dist-info/LICENSE
md2gemini-1.9.1.dist-info/METADATA
md2gemini-1.9.1.dist-info/WHEEL
md2gemini-1.9.1.dist-info/entry_points.txt
md2gemini-1.9.1.dist-info/top_level.txt
md2gemini-1.9.1.dist-info/RECORD
