Metadata-Version: 2.1
Name: md2gemini
Version: 1.9.1
Summary: Convert Markdown to the Gemini text format
Home-page: https://github.com/makeworld-the-better-one/md2gemini
Author: makeworld
Author-email: makeworld@protonmail.com
Classifier: Programming Language :: Python :: 3
Classifier: License :: OSI Approved :: GNU Lesser General Public License v3 (LGPLv3)
Classifier: Operating System :: OS Independent
Classifier: Topic :: Text Processing
Classifier: Topic :: Text Processing :: General
Classifier: Topic :: Text Processing :: Markup
Requires-Python: >=3.7
License-File: LICENSE
Requires-Dist: mistune <3,>=2.0.0
Requires-Dist: cjkwrap
Requires-Dist: wcwidth
